{
  "filename": "WhatsApp Image 2026-01-06 at 21.52.22.jpeg",
  "timestamp": "2026-01-07T05:29:49.173516",
  "file_size": 186168,
  "analysis": {
    "filename": "WhatsApp Image 2026-01-06 at 21.52.22.jpeg",
    "image_type": "Close-up detail",
    "primary_subject": "A series of woven bamboo or rattan ceiling fans mounted on a beige fabric-covered wall",
    "completion_stage": "Completed",
    "technical_details": {
      "materials": [
        "Bamboo/Rattan",
        "Fabric",
        "Metal (for mounting hardware)"
      ],
      "joinery_techniques": [
        "Woven construction",
        "Interlocking joints"
      ],
      "construction_methods": [
        "Handwoven",
        "Mounting hardware installation"
      ]
    },
    "craftsmanship_quality": {
      "precision": "High - The fans are evenly spaced and symmetrically aligned, indicating careful planning and execution.",
      "surface_quality": "High - The woven texture of the fans is smooth and consistent, with no visible flaws or irregularities.",
      "attention_to_detail": "High - The alignment of the fans and the neatness of the fabric covering suggest meticulous attention to detail."
    },
    "design_elements": {
      "style": "Rustic/Traditional",
      "functional_features": [
        "Ceiling fans for air circulation",
        "Aesthetic wall covering"
      ],
      "aesthetic_features": [
        "Natural material texture",
        "Symmetrical arrangement",
        "Neutral color palette"
      ]
    },
    "portfolio_presentation": {
      "best_use": "Detail",
      "accompanying_text": "This image showcases a beautifully crafted series of woven bamboo or rattan ceiling fans mounted on a beige fabric-covered wall. The intricate weaving and precise alignment highlight the craftsmanship and attention to detail, creating a rustic yet elegant aesthetic.",
      "quality_rating": 9
    },
    "keywords": [
      "Bamboo fans",
      "Rattan ceiling fans",
      "Woven craftsmanship",
      "Rustic decor",
      "Interior design",
      "Handwoven",
      "Natural materials",
      "Symmetrical arrangement"
    ],
    "timestamp": "2026-01-07T05:29:49.173516",
    "file_size": 186168
  }
}