{
  "filename": "WhatsApp Image 2026-01-06 at 22.02.07.jpeg",
  "timestamp": "2026-01-07T05:56:06.304660",
  "file_size": 79851,
  "analysis": {
    "filename": "WhatsApp Image 2026-01-06 at 22.02.07.jpeg",
    "image_type": "Full project view",
    "primary_subject": "A kitchen undergoing renovation with visible carpentry work on cabinets and countertops",
    "completion_stage": "Work-in-progress",
    "technical_details": {
      "materials": [
        "Plywood",
        "Laminate",
        "Tile",
        "Metal hardware"
      ],
      "joinery_techniques": [
        "Dovetail joints",
        "Butt joints"
      ],
      "construction_methods": [
        "Modular assembly",
        "Surface mounting"
      ]
    },
    "craftsmanship_quality": {
      "precision": "Medium - [The cabinetry appears to be well-aligned, but some areas show minor misalignments]",
      "surface_quality": "Medium - [The surfaces are smooth but show signs of ongoing finishing work]",
      "attention_to_detail": "High - [The cabinetry design and installation show careful planning and execution]"
    },
    "design_elements": {
      "style": "Modern",
      "functional_features": [
        "Modular cabinetry",
        "Integrated countertops",
        "Under-cabinet lighting"
      ],
      "aesthetic_features": [
        "Clean lines",
        "Uniform color scheme",
        "Minimalist design"
      ]
    },
    "portfolio_presentation": {
      "best_use": "Process",
      "accompanying_text": "This image showcases a modern kitchen undergoing a comprehensive renovation. The focus is on the carpentry work, highlighting the modular cabinetry and integrated countertops. The project demonstrates attention to detail and precision in the assembly and finishing stages.",
      "quality_rating": 7
    },
    "keywords": [
      "Kitchen renovation",
      "Carpentry",
      "Modular cabinetry",
      "Modern design",
      "Work-in-progress"
    ],
    "timestamp": "2026-01-07T05:56:06.304660",
    "file_size": 79851
  }
}