{
  "filename": "WhatsApp Image 2026-01-06 at 22.41.29.jpeg",
  "timestamp": "2026-01-07T06:01:05.292678",
  "file_size": 75020,
  "analysis": {
    "filename": "WhatsApp Image 2026-01-06 at 22.41.29.jpeg",
    "image_type": "Work-in-progress",
    "primary_subject": "Custom kitchen cabinetry and shelving unit under construction",
    "completion_stage": "Assembly",
    "technical_details": {
      "materials": [
        "Plywood",
        "MDF",
        "Paint",
        "Glass",
        "Metal hardware"
      ],
      "joinery_techniques": [
        "Dado joints",
        "Rabbet joints"
      ],
      "construction_methods": [
        "Framing",
        "Panel installation",
        "Cabinet assembly"
      ]
    },
    "craftsmanship_quality": {
      "precision": "Medium - [The alignment of the panels and doors appears mostly accurate, but some minor adjustments may be needed for perfect fit.]",
      "surface_quality": "Medium - [The surfaces are smooth but show some minor imperfections and areas needing touch-up.]",
      "attention_to_detail": "Medium - [The attention to detail is evident in the joinery and alignment, but some finishing touches are still required.]"
    },
    "design_elements": {
      "style": "Modern",
      "functional_features": [
        "Adjustable shelving",
        "Storage cabinets",
        "Integrated countertop"
      ],
      "aesthetic_features": [
        "Clean lines",
        "Minimalist design",
        "Color contrast"
      ]
    },
    "portfolio_presentation": {
      "best_use": "Process",
      "accompanying_text": "This image showcases a custom kitchen cabinetry and shelving unit in the assembly stage. The project highlights the use of modern design elements and precise joinery techniques to create functional and aesthetically pleasing storage solutions.",
      "quality_rating": 7
    },
    "keywords": [
      "kitchen cabinetry",
      "custom shelving",
      "modern design",
      "joinery techniques",
      "work-in-progress"
    ],
    "timestamp": "2026-01-07T06:01:05.292678",
    "file_size": 75020
  }
}